Metadata-Version: 2.1
Name: nr.dotconfig
Version: 0.0.4
Summary: A single configuration file for .bash_profile and .gitconfig.
Home-page: https://git.niklasrosenstein.com/NiklasRosenstein/dotconfig
Author: Niklas Rosenstein
Author-email: rosensteinniklas@gmail.com
License: MIT
Platform: UNKNOWN
